{
  "generatedAt": "2025-11-04T07:09:17.081Z",
  "days": [
    {
      "id": "01-points",
      "dayNumber": 1,
      "title": "Day 1: Points",
      "theme": "Points",
      "relativeUrl": "maps/01-points/index.html",
      "readmeUrl": "maps/01-points/README.md"
    },
    {
      "id": "02-lines",
      "dayNumber": 2,
      "title": "Day 2: Lines",
      "theme": "Lines",
      "relativeUrl": "maps/02-lines/index.html",
      "readmeUrl": "maps/02-lines/README.md"
    },
    {
      "id": "03-polygons",
      "dayNumber": 3,
      "title": "Day 3: Polygons",
      "theme": "Polygons",
      "status": "Complete",
      "relativeUrl": "maps/03-polygons/index.html",
      "readmeUrl": "maps/03-polygons/README.md"
    }
  ]
}
